{
  "type": "object",
  "properties": {
    "data": {
      "type": "object",
      "properties": {
        "posts": {
          "type": "array",
          "items": {
            "type": "object",
            "properties": {
              "rated": {
                "type": "number"
              },
              "hearted": {
                "type": "boolean"
              },
              "img_url": {
                "type": "string"
              },
              "likes": {
                "type": "integer"
              },
              "id": {
                "type": "string"
              },
              "date": {
                "type": "string"
              },
              "content": {
                "type": "string"
              }
            }
          }
        },
        "num": {
          "type": "integer"
        }
      }
    },
    "message": {
      "type": "string"
    }
  }
}
